deckgen/cli.py
deckgen/configs/anki/models.yaml
deckgen/configs/templates/question_asking.txt
deckgen/configs/templates/question_groundedness_critique_prompt.txt
deckgen/configs/templates/topic_finder.txt
deckgen/decks/anki_utils.py
deckgen/decks/base.py
deckgen/decks/generator.py
deckgen/entry.py
deckgen/generation/openai_client.py
deckgen/pipelines/qa_pipeline.py
deckgen/pipelines/validate_qa.py
deckgen/reader/base.py
deckgen/reader/file_reader.py
deckgen/reader/validations.py
deckgen/splitter/document.py
deckgen/splitter/splitters.py
deckgen/splitter/text_splitter.py
deckgen/utils/cli.py
deckgen/utils/files.py
deckgen-0.10.4.dist-info/METADATA
deckgen-0.10.4.dist-info/WHEEL
deckgen-0.10.4.dist-info/entry_points.txt
deckgen-0.10.4.dist-info/RECORD
