Metadata-Version: 2.3
Name: deckgen
Version: 0.10.4
Summary: Tool to create anki decks using generative AI
Author: Manuel Gil
Author-email: manuelgilsitio@gmail.com
Requires-Python: >=3.11,<4.0
Classifier: Programming Language :: Python :: 3
Classifier: Programming Language :: Python :: 3.11
Classifier: Programming Language :: Python :: 3.12
Classifier: Programming Language :: Python :: 3.13
Requires-Dist: genanki (>=0.13.1,<0.14.0)
Requires-Dist: langchain (>=0.3.26,<0.4.0)
Requires-Dist: langchain-experimental (>=0.3.4,<0.4.0)
Requires-Dist: markdown (>=3.8.2,<4.0.0)
Requires-Dist: pypdf (>=5.9.0,<6.0.0)
Requires-Dist: python-dotenv (>=1.1.0,<2.0.0)
Requires-Dist: tqdm (>=4.67.1,<5.0.0)
